{
  "name": "arduino_bpDebounce",
  "version": "0.0.1",
  "license": "MIT",
  "keywords": "Switches, Buttons, Debounced",
  "description": "Arduino library to debounce button switches, detect presses, releases, and long presses.",
  "homepage": "https://github.com/AdriLighting/",
  "repository":
  {
    "type": "git",
    "url": "https://github.com/AdriLighting/arduino_bpDebounce.git"
  },
  "authors": [
    {
      "name": "Grellard Adrien",
      "email": "grellard.adrien@gmail.com",
      "maintainer": true
    }
  ],
  "dependencies": [
    {
        "owner": "Grellard Adrien",
        "name": "arduino_ALmillisTimer",
        "version": "https://github.com/AdriLighting/arduino_ALmillisTimer.git"
    }
    
  ],
  "frameworks": "arduino",
  "platforms": "atmelavr, espressif8266",
  "headers": "bp_debouce.h"
}